README.txt
setup.py
nostrint/__init__.py
nostrint/__main__.py
nostrint/command_line.py
nostrint/no_strint.py
nostrint/obfuscator.py
nostrint/redat.py
nostrint/reindent.py
nostrint/template.py
nostrint/utils.py
strint.egg-info/PKG-INFO
strint.egg-info/SOURCES.txt
strint.egg-info/dependency_links.txt
strint.egg-info/entry_points.txt
strint.egg-info/not-zip-safe
strint.egg-info/top_level.txt