Metadata-Version: 1.0
Name: strint
Version: 1.4.9.642019
Summary: python source code obfuscator. only obscures strings and integers
Home-page: https://github.com/zevtyardt/no-strint
Author: zvtyrdt.id
Author-email: xnver404@gmail.com
License: MIT
Keywords: obf,str,int,obfuscator,source,code
Platform: UNKNOWN
